<DOMSymbolItem xmlns:xsi="http://www.w3.org/2001/XMLSchema-instance" xmlns="http://ns.adobe.com/xfl/2008/" name="Símbolo 29" itemID="5d0aa701-00000096" symbolType="graphic" lastModified="1561061394">
  <timeline>
    <DOMTimeline name="Símbolo 29">
      <layers>
        <DOMLayer name="Capa_1" color="#00FFFF" current="true" isSelected="true">
          <frames>
            <DOMFrame index="0" keyMode="9728">
              <elements>
                <DOMShape>
                  <fills>
                    <FillStyle index="1">
                      <SolidColor/>
                    </FillStyle>
                    <FillStyle index="2">
                      <SolidColor color="#231108"/>
                    </FillStyle>
                  </fills>
                  <strokes>
                    <StrokeStyle index="1">
                      <SolidStroke scaleMode="normal" weight="7">
                        <fill>
                          <SolidColor/>
                        </fill>
                      </SolidStroke>
                    </StrokeStyle>
                  </strokes>
                  <edges>
                    <Edge fillStyle1="2" strokeStyle="1" edges="!160 2723[#41.E #995.1F 55.5 2138!55.5 2138[#2D.5D #71E.A1 115 1505!115 1505[#B8.A2 #4A3.5E 324.5 951.5!324.5 951.5[#1D0.1F #2CB.E 702 503!702 503[935 295 1218 162!1218 162[1486 37 1774 10!1774 10[2075 -18 2374 47!2374 47[2682 110 2955
 264!2955 264[3227 420 3410 678!3410 678[3583 921 3656 1206!3656 1206[3688 1334 3708 1464"/>
                    <Edge fillStyle1="1" edges="
!3696 2052[3701 1975 3701 1969!3701 1969[3701 1902 3688 1831!3688 1831[3684 1809 3678 1786!3678 1786[3661 1718 3633 1647!3633 1647[3547 1429 3342 1152!3342 1152[3338 1147 3311 1123!3311 1123[3282 1097 3275 1093!3275 1093[3255 1081 3214
 1098!3214 1098[3168 1121 3148 1126!3148 1126[2890 1194 2737 1217!2737 1217[2576 1241 2368 1241!2368 1241[2031 1241 1661 1157!1661 1157[1354 1072 1323 1072!1323 1072[1295 1072 1292 1316!1292 1316[1291 1469 1297 1929!1297 1929[1299 2297
 1178 2478!1178 2478[1147 2524 1093 2594!1093 2594[1055 2656 1055 2733!1055 2733[1055 2766 1118 2938!1118 2938[1150 3023 1181 3104!1181 3104[1181 3199 1090 3254!1090 3254[1024 3294 971 3294!971 3294[917 3294 881 3203!881 3203[842 3077
 818 3004!818 3004[723 2714 502 2714!502 2714[349 2714 256 2819!256 2819[244 2833 234 2847!234 2847[193 2788 160 2723"/>
                    <Edge fillStyle0="2" fillStyle1="1" edges="
!160 2723[179 2704 202 2686!202 2686[346 2576 512 2576!512 2576[635 2576 732 2643!732 2643[805 2693 890 2805!890 2805[916 2791 937 2673!937 2673[963 2532 1033 2437!1033 2437[1119 2321 1124 2312!1124 2312[1147 2276 1158 2225!1158 2225
[1162 2204 1152 1397!1152 1397[1151 990 1168 928!1168 928[1172 913 1188 904!1188 904[1203 896 1224 896!1224 896[1265 896 1562 1000!1562 1000[1938 1104 2367 1104!2367 1104[2768 1104 3020 1020!3020 1020[3051 1010 3168 962!3168 962[3233
 936 3272 936!3272 936[3320 936 3419 1041!3419 1041[3522 1149 3618 1305!3618 1305[3668 1386 3708 1464"/>
                    <Edge fillStyle1="1" edges="
!3708 1464[3752 1780 3696 2052"/>
                    <Edge cubics="!160 2723(;259,2627 400,2576 512,2576q160 2723 202 2686Q346 2576q512 2576);"/>
                    <Edge cubics="!512 2576(;691,2576 793,2677 890,2805q512 2576Q635 2576q732 2643Q805 2693q890 2805);"/>
                    <Edge cubics="!890 2805(;952,2772 906,2609 1033,2437q890 2805Q916 2791q937 2673Q963 2532q1033 2437);"/>
                    <Edge cubics="!1033 2437(;1126,2311 1142,2300 1158,2225q1033 2437Q1119 2321q1124 2312Q1147 2276q1158 2225);"/>
                    <Edge cubics="!1158 2225(;1162,2204 1152,1417 1152,1397q1158 2225Q1162 2204q1152 1397);"/>
                    <Edge cubics="!1152 1397(;1152,1377 1151,990 1168,928q1152 1397Q1151 990q1168 928);"/>
                    <Edge cubics="!1168 928(;1173,907 1198,896 1224,896q1168 928Q1172 913q1188 904Q1203 896q1224 896);"/>
                    <Edge cubics="!1224 896(;1305,896 1664,1104 2367,1104q1224 896Q1265 896q1562 1000Q1938 1104q2367 1104);"/>
                    <Edge cubics="!2367 1104(;3036,1104 3137,936 3272,936q2367 1104Q2768 1104q3020 1020Q3051 1010q3168 962Q3233 936q3272 936);"/>
                    <Edge cubics="!3272 936(;3350,936 3567,1180 3708,1464q3272 936Q3320 936q3419 1041Q3522 1149q3618 1305 3708 1464);"/>
                    <Edge cubics="!2368 1241(;1816,1241 1384,1072 1323,1072q2368 1241Q2031 1241q1661 1157Q1354 1072q1323 1072);"/>
                    <Edge cubics="!1323 1072(;1279,1072 1294,1438 1297,1929q1323 1072Q1295 1072q1292 1316Q1291 1469q1297 1929);"/>
                    <Edge cubics="!1297 1929(;1301,2566 1055,2489 1055,2733q1297 1929Q1299 2297q1178 2478Q1147 2524q1093 2594Q1055 2656q1055 2733);"/>
                    <Edge cubics="!1055 2733(;1055,2787 1181,3101 1181,3104q1055 2733Q1055 2766q1118 2938Q1150 3023q1181 3104);"/>
                    <Edge cubics="!1181 3104(;1181,3251 1008,3294 971,3294q1181 3104Q1181 3199q1090 3254Q1024 3294q971 3294);"/>
                    <Edge cubics="!971 3294(;801,3294 890,2714 502,2714q971 3294Q917 3294q881 3203Q842 3077q818 3004Q723 2714q502 2714);"/>
                    <Edge cubics="!3696 2052(;3699,2005 3701,1974 3701,1969q3696 2052 3701 1969);"/>
                    <Edge cubics="!3701 1969(;3701,1930 3698,1887 3688,1831q3701 1969Q3701 1902q3688 1831);"/>
                    <Edge cubics="!3688 1831(;3686,1821 3682,1804 3678,1786q3688 1831 3678 1786);"/>
                    <Edge cubics="!3342 1152(;3338,1147 3286,1099 3275,1093q3342 1152Q3338 1147q3311 1123Q3282 1097q3275 1093);"/>
                    <Edge cubics="!3275 1093(;3242,1073 3187,1115 3148,1126q3275 1093Q3255 1081q3214 1098Q3168 1121q3148 1126);"/>
                    <Edge cubics="!3148 1126(;2810,1215 2650,1241 2368,1241q3148 1126Q2890 1194q2737 1217Q2576 1241q2368 1241);"/>
                    <Edge cubics="!3708 1464(;3738,1679 3734,1876 3696,2052q3708 1464Q3752 1780q3696 2052);"/>
                    <Edge cubics="!256 2819(;248,2828 241,2838 234,2847q256 2819Q244 2833q234 2847);"/>
                    <Edge cubics="!502 2714(;400,2714 318,2749 256,2819q502 2714Q349 2714q256 2819);"/>
                    <Edge cubics="!3633 1647(;3576,1502 3479,1337 3342,1152q3633 1647Q3547 1429q3342 1152);"/>
                    <Edge cubics="!3678 1786(;3667,1741 3652,1694 3633,1647q3678 1786Q3661 1718q3633 1647);"/>
                    <Edge cubics="!234 2847(;207,2808 182,2766 160,2723q234 2847Q193 2788q160 2723);"/>
                    <Edge cubics="!3656 1206(;3677,1291 3695,1377 3708,1464q3656 1206Q3688 1334q3708 1464);"/>
                    <Edge cubics="!3410 678(;3525,840 3607,1016 3656,1206q3410 678Q3583 921q3656 1206);"/>
                    <Edge cubics="!1774 10(;1975,-9 2175,4 2374,47q1774 10Q2075 -18q2374 47);"/>
                    <Edge cubics="!2374 47(;2579,89 2773,161 2955,264q2374 47Q2682 110q2955 264);"/>
                    <Edge cubics="!293 985(;407,806 543,645 702,503q293 985Q464 716q702 503);"/>
                    <Edge cubics="!702 503(;857,364 1029,251 1218,162q702 503Q935 295q1218 162);"/>
                    <Edge cubics="!61 1532(;108,1337 186,1155 293,985q61 1532Q132 1240q293 985);"/>
                    <Edge cubics="!160 2723(;66,2543 14,2351 3,2146q160 2723Q19 2453q3 2146);"/>
                    <Edge cubics="!1218 162(;1397,79 1582,28 1774,10q1218 162Q1486 37q1774 10);"/>
                    <Edge cubics="!3 2146(;-8,1938 12,1733 61,1532q3 2146Q-13 1834q61 1532);"/>
                    <Edge cubics="!2955 264(;3136,368 3288,506 3410,678q2955 264Q3227 420q3410 678);"/>
                  </edges>
                </DOMShape>
              </elements>
            </DOMFrame>
          </frames>
        </DOMLayer>
      </layers>
    </DOMTimeline>
  </timeline>
</DOMSymbolItem>